[
	{
		"nombre": "ABRAXAS",
		"direccion": "DONATO GUERRA N° 9, COL TIZAPAN",
		"pais": "MÉXICO",
		"entidad": "NUEVO LEON",
		"iso": "MX",
		"bd": true
	},
	{
		"nombre": "BENEMERITA UNIVERSIDAD AUTONOMA DE PUEBLA",
		"direccion": "CALLE 4 SUR 104, CENTRO, 5013 HEROICA PUEBLA DE ZARAGOZA, PUE",
		"pais": "MÉXICO",
		"entidad": "PUEBLA",
		"iso": "MX",
		"bd": true
	},
	{
		"nombre": "BIOTECH DEL NORTE",
		"direccion": "AV. VASCONCELOS N° 150 OTE. 66220, SAN PEDRO GARZA, NL",
		"pais": "MÉXICO",
		"entidad": "NUEVO LEON",
		"iso": "MX",
		"bd": true
	},
	{
		"nombre": "CENTRO DE INVESTIGACION BIOMEDICA DE ORIENTE. INSTITUTO MEXICANO DEL SEGURO SOCIAL",
		"direccion": "CARRETERA FEDERAL ATLIXCO METEPEC KM. 4.5, COL. CENTRO, ATLIXCO, C.P. 74360",
		"pais": "MÉXICO",
		"entidad": "PUEBLA",
		"iso": "MX",
		"bd": true
	},
	{
		"nombre": "CENTRO DE INVESTIGACION CIENTIFICA Y EDUCACION SUPERIOR DE ENSENADA",
		"direccion": "CARR. ENSENADA, TIJANA, N° 3918, ZONA PLAYITAS, CP 22680",
		"pais": "MÉXICO",
		"entidad": "BAJA CALIFORNIA",
		"iso": "MX",
		"bd": true
	},
	{
		"nombre": "CENTRO DE INVESTIGACION DE INGENIERIA GENETICA-BIOTECNOLOGICA",
		"direccion": "CUERNAVACA",
		"pais": "MÉXICO",
		"entidad": "MORELOS",
		"iso": "MX",
		"bd": true
	},
	{
		"nombre": "CENTRO DE INVESTIGACION Y DE ESTUDIOS AVANZADOS. INSTITUTO POLITECNICO NACIONAL",
		"direccion": "AV. INSTITUTO POLITECNICO NACIONAL 2508, COL. SAN PEDRO ZACATENCO, CP 073660 ",
		"pais": "MÉXICO",
		"entidad": "CIUDAD DE MEXICO",
		"iso": "MX",
		"bd": true
	},
	{
		"nombre": "CENTRO DE ONCOLOGIA PERSONALIZADA / CENTRO DE INVESTIGACION ONCOLOGICA",
		"direccion": "AV JUAN ESCUTIA 1680, CHAPULTEPEC, CULIACAN, SIN, C.P.80040",
		"pais": "MÉXICO",
		"entidad": "SINALOA",
		"iso": "MX",
		"bd": true
	},
	{
		"nombre": "CENTRO INTERDISCIPLINARIO DE CIENCAS DE LA SALUD",
		"direccion": "CARRETERA XOCHIMILCO-OAXTEPEC KM 39.5, MILPA ALTA",
		"pais": "MÉXICO",
		"entidad": "CIUDAD DE MEXICO",
		"iso": "MX",
		"bd": true
	},
	{
		"nombre": "CENTRO INVESTIGACION DE ENFERMEDADES INFECCIOSAS",
		"direccion": "CALZADA DE TLALPAN N° 4502, CP 14080",
		"pais": "MÉXICO",
		"entidad": "CIUDAD DE MEXICO",
		"iso": "MX",
		"bd": true
	},
	{
		"nombre": "CENTRO MEDICO NACIONAL SIGLO XXI. INSTITUTO MEXICANO DEL SEGURO SOCIAL",
		"direccion": "CUAUHTECMOC 330 CP 06725",
		"pais": "MÉXICO",
		"entidad": "CIUDAD DE MEXICO",
		"iso": "MX",
		"bd": true
	},
	{
		"nombre": "CENTRO UNIVERSITARIO DE CIENCIAS DE LA SALUD",
		"direccion": "SIERRA MOJADA 950, COL. INDEPENDENCIA, GUADALAJARA, C.P. 44340",
		"pais": "MÉXICO",
		"entidad": "JALISCO",
		"iso": "MX",
		"bd": true
	},
	{
		"nombre": "CLINICA ONCOSALUD",
		"direccion": "Av. Guardia Civil 571, San Borja 15036",
		"pais": "PERÚ",
		"entidad": "LIMA",
		"iso": "PE",
		"bd": true
	},
	{
		"nombre": "COLEGIO ALEMAN ALEXANDER VON HUMBOLDT",
		"direccion": "PRADO NORTE N° 559, CP 11000, CIUDAD DE MEXICO",
		"pais": "MÉXICO",
		"entidad": "CIUDAD DE MEXICO",
		"iso": "MX",
		"bd": true
	},
	{
		"nombre": "ESCUELA SUPERIOR DE MEDICINA. INSTITUTO POLITECNICO NACIONAL",
		"direccion": "PLAN DE SAN LUIS,  COL. CASCO SANTO TOMAS, DEL. MIGUEL HIDALGO, CIUDAD DE MEXICO , C.P. 11340 ",
		"pais": "MÉXICO",
		"entidad": "CIUDAD DE MEXICO",
		"iso": "MX",
		"bd": true
	},
	{
		"nombre": "FACULTAD DE CIENCIAS QUIMICO BIOLOGICAS. UNIVERSIDAD AUTONOMA DE GUERRERO",
		"direccion": "LAZARO CARDENAS, COL. EL CENTENARIO, CHILPANCINGO DE LOS BRAVO",
		"pais": "MÉXICO",
		"entidad": "GUERRERO",
		"iso": "MX",
		"bd": true
	},
	{
		"nombre": "FACULTAD DE ESTUDIOS SUPERIORES IZTACALA. UNIVERSIDAD NACIONAL AUTONOMA DE MEXICO",
		"direccion": "AV DE LOS BARRIOS 1, COL. LOS REYES IXTACALA, TLALNEPANTLA, C.P. 54090",
		"pais": "MÉXICO",
		"entidad": "ESTADO DE MEXICO",
		"iso": "MX",
		"bd": true
	},
	{
		"nombre": "FACULTAD DE ESTUDIOS SUPERIORES ZARAGOZA. UNIVERSIDAD NACIONAL AUTONOMA DE MEXICO",
		"direccion": "CALZADA I. ZARAGOZA 09230, CIUDAD DE MEXICO",
		"pais": "MÉXICO",
		"entidad": "CIUDAD DE MEXICO",
		"iso": "MX",
		"bd": true
	},
	{
		"nombre": "HOSPITAL CENTRAL SUR DE ALTA ESPECIALIDAD. PETROLEOS MEXICANOS",
		"direccion": "ANILLO PERIFERICO 4091, FUENTES DEL PEDREGAL, DEL. TLALPAN, C.P. 14140",
		"pais": "MÉXICO",
		"entidad": "CIUDAD DE MEXICO",
		"iso": "MX",
		"bd": true
	},
	{
		"nombre": "HOSPITAL DE ONCOLOGIA CENTRO MEDICO NACIONAL SIGLO XXI. INSTITUTO MEXICANO DEL SEGURO SOCIAL",
		"direccion": "CUAUHTECMOC 330, COL.  DOCTORES, CIUDAD DE MEXICO, C.P. 06725",
		"pais": "MÉXICO",
		"entidad": "CIUDAD DE MEXICO",
		"iso": "MX",
		"bd": true
	},
	{
		"nombre": "HOSPITAL GEA GONZALEZ",
		"direccion": "CALZADA DE TLALPAN N° 4800, CP 14080. CIUDAD DE MEX.",
		"pais": "MÉXICO",
		"entidad": "CIUDAD DE MEXICO",
		"iso": "MX",
		"bd": true
	},
	{
		"nombre": "HOSPITAL GENERAL DE ZONA 30. INSTITUTO MEXICANO DEL SEGURO SOCIAL",
		"direccion": "PLUTARCO ELIAS CALLES 473, COL. SANTA ANITA, DEL. IZTACALCO",
		"pais": "MÉXICO",
		"entidad": "CIUDAD DE MEXICO",
		"iso": "MX",
		"bd": true
	},
	{
		"nombre": "HOSPITAL GENERAL DR RAYMUNDO ABARCA ALARCON",
		"direccion": "AV. GUERRERO 45, COL. CENTRO, CHILPANCINGO, C.P. 39000",
		"pais": "MÉXICO",
		"entidad": "GUERRERO",
		"iso": "MX",
		"bd": true
	},
	{
		"nombre": "HOSPITAL INFANTIL DE MEXICO FEDERICO GOMEZ",
		"direccion": "CALLE SUR 169, 2404, CP 08000 IZTACALCO",
		"pais": "MÉXICO",
		"entidad": "CIUDAD DE MEXICO",
		"iso": "MX",
		"bd": true
	},
	{
		"nombre": "HOSPITAL JOSE MARIA CABRAL Y BAEZ",
		"direccion": "Av Franco Bido, Santiago De Los Caballeros 51000",
		"pais": "REPÚBLICA DOMINICANA",
		"entidad": "SANTO DOMINGO",
		"iso": "DO",
		"bd": true
	},
	{
		"nombre": "HOSPITAL JUAREZ DE MEXICO",
		"direccion": "AV. INSTITUTO POLITECNICO NACIONAL 5160, COL. MAGDALENA DE LAS SALINAS, CP 07760",
		"pais": "MÉXICO",
		"entidad": "CIUDAD DE MEXICO",
		"iso": "MX",
		"bd": true
	},
	{
		"nombre": "HOSPITAL REGIONAL DE ALTA ESPECIALIDAD BAJIO",
		"direccion": "BLVD. MILENIO 130, COL. SAN CARLOS LA ROCHA, LEON",
		"pais": "MÉXICO",
		"entidad": "GUANAJUATO",
		"iso": "MX",
		"bd": true
	},
	{
		"nombre": "HOSPITAL REGIONAL DE ALTA ESPECIALIDAD CIUDAD SALUD",
		"direccion": "CARR. TAPACHULA - PUERTO MADERO KM. 15 +200, TAPACHULA",
		"pais": "MÉXICO",
		"entidad": "CHIAPAS",
		"iso": "MX",
		"bd": true
	},
	{
		"nombre": "INSTITUTO NACIONAL DE CANCEROLOGIA",
		"direccion": "SAN FERNANDO NO. 22, COL. SECCION XVI, DEL. TLALPAN, C.P. 14080",
		"pais": "MÉXICO",
		"entidad": "CIUDAD DE MEXICO",
		"iso": "MX",
		"bd": true
	},
	{
		"nombre": "INSTITUTO NACIONAL DE CIENCIAS MEDICAS Y NUTRICION SALVADOR ZUBIRAN",
		"direccion": "VASCO DE QUIROGA 15, SECCION XVI, DEL. TLALPAN, C.P. 14080",
		"pais": "MÉXICO",
		"entidad": "CIUDAD DE MEXICO",
		"iso": "MX",
		"bd": true
	},
	{
		"nombre": "INSTITUTO NACIONAL DE ENFERMEDADES RESPIRATORIAS",
		"direccion": "CALZADA DE TLALPAN 4502, COL. SECCION XVI, DEL. TLALPAN, C.P. 14080",
		"pais": "MÉXICO",
		"entidad": "CIUDAD DE MEXICO",
		"iso": "MX",
		"bd": true
	},
	{
		"nombre": "INSTITUTO NACIONAL DE INVESTIGACIONES NUCLEARES",
		"direccion": "CARRETERA MEXICO TOLUCA - LA MARQUESA, OCOYOACAN, C.P. 52750",
		"pais": "MÉXICO",
		"entidad": "ESTADO DE MEXICO",
		"iso": "MX",
		"bd": true
	},
	{
		"nombre": "INSTITUTO NACIONAL DE MEDICINA GENOMICA",
		"direccion": "PERIFERICO SUR 4809, COL. ARENAL TEPEPAN, CIUDAD DE MEXICO, C.P. 14610",
		"pais": "MÉXICO",
		"entidad": "CIUDAD DE MEXICO",
		"iso": "MX",
		"bd": true
	},
	{
		"nombre": "INSTITUTO NACIONAL DE NEUROLOGIA",
		"direccion": "INSURGENTES SUR 3877, COL. LA FAMA, DELEG. TLALPAN",
		"pais": "MÉXICO",
		"entidad": "CIUDAD DE MEXICO",
		"iso": "MX",
		"bd": true
	},
	{
		"nombre": "INSTITUTO NACIONAL DE PEDIATRIA",
		"direccion": "AV. INSURGENTES SUR 3700 C, COL. INSURGENTES CUICUILCO, DEL. COYOACAN, C.P. 04530",
		"pais": "MÉXICO",
		"entidad": "CIUDAD DE MEXICO",
		"iso": "MX",
		"bd": true
	},
	{
		"nombre": "INSTITUTO NACIONAL DE SALUD PUBLICA",
		"direccion": "AV. UNIVERSIDAD 655, COL. SANTA MARIA AHUACATITLAN, CUERNAVACA, C.P. 62100",
		"pais": "MÉXICO",
		"entidad": "MORELOS",
		"iso": "MX",
		"bd": true
	},
	{
		"nombre": "INSTITUTO NACIONAL DEL CANCER ROSA EMILIA SANCHEZ PEREZ DE TAVAREZ",
		"direccion": "Ave. Dr. Bernardo Correa y Cidrón Esq. Rafael Augusto Sanchéz Ravelo Zona Universitaria",
		"pais": "REPÚBLICA DOMINICANA",
		"entidad": "SANTO DOMINGO",
		"iso": "DO",
		"bd": true
	},
	{
		"nombre": "INSTITUTO TECNOLOGICO DE MONTERREY",
		"direccion": "CALLE DEL PUENTE 222, COL. EJIDOS DE HUIPULCO, DEL. TLALPAN, C.P. 14380",
		"pais": "MÉXICO",
		"entidad": "CIUDAD DE MEXICO",
		"iso": "MX",
		"bd": true
	},
	{
		"nombre": "INVESTIGACION CLINICA A LA SALUD DE CORDOBA S.C.",
		"direccion": "32 NUM. 3219, DOS CAMINOS, CORDOBA",
		"pais": "MÉXICO",
		"entidad": "VERACRUZ",
		"iso": "MX",
		"bd": true
	},
	{
		"nombre": "JOHNS HOPKINS UNIVERSITY SCHOOL OF MEDICINE",
		"direccion": "550 NORTH BROADWAY, SUITE 1103, BALTIMORE",
		"pais": "ESTADOS UNIDOS",
		"entidad": "MARYLAND",
		"iso": "US",
		"bd": true
	},
	{
		"nombre": "LABORATORIOS COLUMBIA SA DE CV",
		"direccion": "CALZADA DEL HUESO 670, COL. GRANJAS COAPA, CP 14307",
		"pais": "MÉXICO",
		"entidad": "CIUDAD DE MEXICO",
		"iso": "MX",
		"bd": true
	},
	{
		"nombre": "MD ANDERSON CANCER CENTER",
		"direccion": "1515 HOLCOMBE BLVD, HOUSTON",
		"pais": "ESTADOS UNIDOS",
		"entidad": "TEXAS",
		"iso": "US",
		"bd": true
	},
	{
		"nombre": "PPD MEXICO",
		"direccion": "INSURGENTES SUR 730, NAPOLES, 03100",
		"pais": "MÉXICO",
		"entidad": "CIUDAD DE MEXICO",
		"iso": "MX",
		"bd": true
	},
	{
		"nombre": "SALUD DE TLAXCALA - SECRETARIA DE SALUD EN EL ESTADO DE TLAXCALA",
		"direccion": "AVENIDA IGNACIO PICAZO NORTE 25, DE TLAPACOYA, CENTRO, 90800 CHIAUTEMPAN",
		"pais": "MÉXICO",
		"entidad": "TLAXCALA",
		"iso": "MX",
		"bd": true
	},
	{
		"nombre": "TECNOLOGICO DE MONTERREY, MONTERREY",
		"direccion": "AV. EUGENIO GARZA SADA 2501 SUR, TECNOLOGICO, C.P. 64849",
		"pais": "MÉXICO",
		"entidad": "NUEVO LEON",
		"iso": "MX",
		"bd": true
	},
	{
		"nombre": "UC SAN DIEGO – MOORES CANCER CENTER",
		"direccion": "Health Sciences Dr, La Jolla",
		"pais": "ESTADOS UNIDOS",
		"entidad": "CALIFORNIA",
		"iso": "US",
		"bd": true
	},
	{
		"nombre": "UNIDAD MEDICA DE ALTA ESPECIALIDAD 71, IMSS",
		"direccion": "BLVD REVOLUCION Y CALLE 27 S/N, TORREON JARDIN, CP. 27000",
		"pais": "MÉXICO",
		"entidad": "COAHUILA",
		"iso": "MX",
		"bd": true
	},
	{
		"nombre": "UNIVERSIDAD AUTONOMA DE AGUASCALIENTES",
		"direccion": "AV. UNIVERSIDAD N° 940 CIUDAD UNIVERSITARIA, AGUASALIENTES, C.P. 20131",
		"pais": "MÉXICO",
		"entidad": "AGUASCALIENTES",
		"iso": "MX",
		"bd": true
	},
	{
		"nombre": "UNIVERSIDAD AUTONOMA DE BAJA CALIFORNIA",
		"direccion": "AV ALVARO OBREGON, COL. NUEVA, MEXICALI, CP 21100",
		"pais": "MÉXICO",
		"entidad": "BAJA CALIFORNIA",
		"iso": "MX",
		"bd": true
	},
	{
		"nombre": "UNIVERSIDAD AUTONOMA DE QUERETARO",
		"direccion": "CERRO DE LAS CAMPANAS, CENTRO UNIVERSITARIO, C.P. 76010",
		"pais": "MÉXICO",
		"entidad": "QUERETARO",
		"iso": "MX",
		"bd": true
	},
	{
		"nombre": "UNIVERSIDAD AUTONOMA DE SANTO DOMINGO",
		"direccion": "Av. Dr. Bernardo Correa y Cidrón",
		"pais": "REPÚBLICA DOMINICANA",
		"entidad": "SANTO DOMINGO",
		"iso": "DO",
		"bd": true
	},
	{
		"nombre": "UNIVERSIDAD AUTONOMA DE YUCATAN",
		"direccion": "CALLE 60 491A, CENTRO, MERIA, C.P. 97000",
		"pais": "MÉXICO",
		"entidad": "YUCATÁN",
		"iso": "MX",
		"bd": true
	},
	{
		"nombre": "UNIVERSIDAD AUTONOMA DEL ESTADO DE HIDALGO",
		"direccion": "CARRETERA PACHUCA - ACTOPAN KM 4.5 CAMPO DE TIRO 42039, PACHUCA DE SOTO",
		"pais": "MÉXICO",
		"entidad": "HIDALGO",
		"iso": "MX",
		"bd": true
	},
	{
		"nombre": "UNIVERSIDAD AUTONOMA METROPOLITANA IZTAPALAPA",
		"direccion": "AV. SAN RAFAEL ATLIXCO 186, COL.VICENTINA, DEL. IZTAPALAPA, C.P.09340",
		"pais": "MÉXICO",
		"entidad": "CIUDAD DE MEXICO",
		"iso": "MX",
		"bd": true
	},
	{
		"nombre": "UNIVERSIDAD AUTONOMA METROPOLITANA XOCHIMILCO",
		"direccion": "CALZADA DEL HUESO 1100, COL. VILLA QUIETUD, DEL. COYOACAN, C.P. 04960",
		"pais": "MÉXICO",
		"entidad": "CIUDAD DE MEXICO",
		"iso": "MX",
		"bd": true
	},
	{
		"nombre": "UNIVERSIDAD DE GUADALAJARA",
		"direccion": "SIERRA MOJADA 950, COL INDEPENDENCIA, GUADALAJARA",
		"pais": "MÉXICO",
		"entidad": "JALISCO",
		"iso": "MX",
		"bd": true
	},
	{
		"nombre": "UNIVERSIDAD DE GUANAJUATO",
		"direccion": "LASCUARAN DE RETANA N° 5, CENTRO CP 36000, GUANAJUATO",
		"pais": "MÉXICO",
		"entidad": "GUANAJUATO",
		"iso": "MX",
		"bd": true
	},
	{
		"nombre": "UNIVERSIDAD DE MONTERREY",
		"direccion": "AV. MORONES PRIETO 4500, 66236 SAN PEDRO GARZA NL",
		"pais": "MÉXICO",
		"entidad": "NUEVO LEON",
		"iso": "MX",
		"bd": true
	},
	{
		"nombre": "UNIVERSIDAD DE SONORA",
		"direccion": "BLVD. LUIS ENCINAS Y ROSALES S/N, COL. CENTRO. HERMOSILLO",
		"pais": "MÉXICO",
		"entidad": "SONORA",
		"iso": "MX",
		"bd": true
	},
	{
		"nombre": "UNIVERSIDAD JUAREZ AUTONOMA DE TABASCO",
		"direccion": "AV. UNIVERSIDAD S/N, COL MAGISTERIAL, VILLAHERMOSA",
		"pais": "MÉXICO",
		"entidad": "TABASCO",
		"iso": "MX",
		"bd": true
	},
	{
		"nombre": "UNIVERSIDAD NACIONAL AUTONOMA DE MEXICO",
		"direccion": "AV. UNIVERSIDAD 3000, CIUDAD UNIVERSITARIA, DEL. COYOACAN, C.P. 04510",
		"pais": "MÉXICO",
		"entidad": "CIUDAD DE MEXICO",
		"iso": "MX",
		"bd": true
	},
	{
		"nombre": "UNIVERSIDAD OLMECA",
		"direccion": "CARR. VILLAHERMOSA-MACUSPANA KM 14, DOS MONTES, VILLAHERMOSA, C.P. 86280",
		"pais": "MÉXICO",
		"entidad": "TABASCO",
		"iso": "MX",
		"bd": true
	},
	{
		"nombre": "UNIVERSIDAD POPULAR AUTONOMA DEL ESTADO DE PUEBLA",
		"direccion": "CALLE 21 SUR 1103, BARRIO DE SANTIAGO, 72410",
		"pais": "MÉXICO",
		"entidad": "PUEBLA",
		"iso": "MX",
		"bd": true
	},
	{
		"nombre": "UNIVERSIDAD VERACRUZANA XALAPA",
		"direccion": "ZAMORA 25, COL. CENTRO, XALAPA-ENRIQUEZ, C.P. 91000",
		"pais": "MÉXICO",
		"entidad": "VERACRUZ",
		"iso": "MX",
		"bd": true
	},
	{
		"nombre": "UNIVERSITY OF MINNESOTA",
		"direccion": "424 SE HARVARD ST, MINNEAPOLIS",
		"pais": "ESTADOS UNIDOS",
		"entidad": "MINNESOTA",
		"iso": "US",
		"bd": true
	},
	{
		"nombre": "VITAGENESIS SA DE CV",
		"direccion": "BLVD. PUERTA DEL SOL 1005, COLINAS DE SAN JEMO 3O SECTOR, MONTERREY",
		"pais": "MÉXICO",
		"entidad": "NUEVO LEON",
		"iso": "MX",
		"bd": true
	},
	{
		"nombre": "YALE SCHOOL OF MEDICINE",
		"direccion": "333 CEDAR ST, NEW HAVEN",
		"pais": "ESTADOS UNIDOS",
		"entidad": "CONNECTICUT",
		"iso": "US",
		"bd": true
	},
	{
		"nombre": "OTRA",
		"direccion": "",
		"pais": "",
		"entidad": "",
		"iso": "",
		"bd": true
	}
]